{"assets":{"92C74656B088334F9F2FD2DB2984453E":{"type":"texture","index":4,"assetRequest":{"type":"slide","state":"outgoing","slide":"DBE36A64-2E0A-4081-B18E-41A886CE9796"},"url":{"web":"assets/92C74656B088334F9F2FD2DB2984453E.svg"},"width":1024,"height":768},"9FAF5A2DB752E24F36126B2017AAB0F8":{"type":"texture","index":5,"assetRequest":{"type":"slide","state":"incoming","slide":"A52F8ADF-192F-425E-AACB-3035A8FBC65E"},"url":{"web":"assets/9FAF5A2DB752E24F36126B2017AAB0F8.svg"},"width":1024,"height":768}},"events":[{"effects":[{"beginTime":0,"baseLayer":{"animations":[],"initialState":{"affineTransform":[1,0,0,1,0,0],"masksToBounds":false,"rotation":0,"scale":1,"position":{"pointX":512,"pointY":384},"width":1024,"sublayerTransform":[1,0,0,0,0,1,0,0,0,0,1,0,0,0,0,1],"contentsRect":{"y":0,"x":0,"width":1,"height":1},"opacity":1,"edgeAntialiasingMask":251658240,"height":768,"hidden":false,"anchorPoint":{"pointX":0.5,"pointY":0.5}},"objectID":"0","layers":[{"animations":[],"initialState":{"affineTransform":[1,0,0,1,0,0],"masksToBounds":false,"rotation":0,"scale":1,"position":{"pointX":512,"pointY":384},"width":1024,"sublayerTransform":[1,0,0,0,0,1,0,0,0,0,1,-0.0004922987690640373,0,0,0,1],"contentsRect":{"y":0,"x":0,"width":1,"height":1},"opacity":1,"edgeAntialiasingMask":251658240,"height":768,"hidden":false,"anchorPoint":{"pointX":0.5,"pointY":0.5}},"layers":[{"animations":[],"layers":[],"initialState":{"affineTransform":[1,0,0,1,0,0],"masksToBounds":false,"rotation":0,"scale":1,"position":{"pointX":512,"pointY":384},"width":1024,"sublayerTransform":[1,0,0,0,0,1,0,0,0,0,1,0,0,0,0,1],"contentsRect":{"y":0,"x":0,"width":1,"height":1},"opacity":1,"edgeAntialiasingMask":0,"height":768,"hidden":false,"anchorPoint":{"pointX":0.5,"pointY":0.5}},"texture":"9FAF5A2DB752E24F36126B2017AAB0F8"},{"animations":[{"timeOffset":0,"from":{"scalar":false},"beginTime":0,"repeatCount":0,"fillMode":"both","property":"hidden","autoreverses":false,"duration":0.01,"to":{"scalar":true}}],"layers":[],"initialState":{"affineTransform":[1,0,0,1,0,0],"masksToBounds":false,"rotation":0,"scale":1,"position":{"pointX":512,"pointY":384},"width":1024,"sublayerTransform":[1,0,0,0,0,1,0,0,0,0,1,0,0,0,0,1],"contentsRect":{"y":0,"x":0,"width":1,"height":1},"opacity":1,"edgeAntialiasingMask":0,"height":768,"hidden":false,"anchorPoint":{"pointX":0.5,"pointY":0.5}},"texture":"92C74656B088334F9F2FD2DB2984453E"}]}]},"effects":[],"duration":0.01,"type":"transition","name":"none","objectID":"0"}],"automaticPlay":false,"hyperlinks":[],"accessibility":[{"text":"2. Applicants","targetRectangle":{"y":175.7771685123444,"x":806.2825144195557,"width":117.8199999999999,"height":24}},{"text":"Electronic Permit System: Core Components","targetRectangle":{"y":2.133332252502441,"x":139.3750099658966,"width":759.1500000000001,"height":114.5946854698741}},{"text":"6.3 Physical Archive","targetRectangle":{"y":472.9802629947662,"x":426.3975046539306,"width":180.8200000000001,"height":24}},{"text":"6.1 Online Front Page","targetRectangle":{"y":276.8436357975006,"x":419.7175046539306,"width":194.1800000000001,"height":24}},{"text":"6.4 Mobile access","targetRectangle":{"y":568.0504839420319,"x":435.1075046539307,"width":163.4,"height":24}},{"text":"3. Legal","targetRectangle":{"y":377.9101030826569,"x":122.6774817657471,"width":72.25999999999999,"height":24}},{"text":"1. Authorities","targetRectangle":{"y":175.7771685123444,"x":100.4474817657471,"width":116.72,"height":24}},{"text":"4. Monitoring","targetRectangle":{"y":472.9802629947662,"x":100.4574817657471,"width":116.7,"height":24}},{"text":"6.2 Backups","targetRectangle":{"y":377.9101030826569,"x":460.6675046539307,"width":112.28,"height":24}},{"text":"5. Reporting","targetRectangle":{"y":568.0504839420319,"x":103.6074817657471,"width":110.4,"height":24}},{"text":"6. Core System","targetRectangle":{"y":175.777170419693,"x":448.6375103759765,"width":136.3400000000001,"height":24}}],"baseLayer":{"animations":[],"initialState":{"affineTransform":[1,0,0,1,0,0],"masksToBounds":false,"rotation":0,"scale":1,"position":{"pointX":512,"pointY":384},"width":1024,"sublayerTransform":[1,0,0,0,0,1,0,0,0,0,1,0,0,0,0,1],"contentsRect":{"y":0,"x":0,"width":1,"height":1},"opacity":1,"edgeAntialiasingMask":251658240,"height":768,"hidden":false,"anchorPoint":{"pointX":0.5,"pointY":0.5}},"objectID":"0","layers":[{"animations":[],"initialState":{"affineTransform":[1,0,0,1,0,0],"masksToBounds":false,"rotation":0,"scale":1,"position":{"pointX":512,"pointY":384},"width":1024,"sublayerTransform":[1,0,0,0,0,1,0,0,0,0,1,-0.0004922987690640373,0,0,0,1],"contentsRect":{"y":0,"x":0,"width":1,"height":1},"opacity":1,"edgeAntialiasingMask":251658240,"height":768,"hidden":false,"anchorPoint":{"pointX":0.5,"pointY":0.5}},"layers":[{"animations":[],"layers":[],"initialState":{"affineTransform":[1,0,0,1,0,0],"masksToBounds":false,"rotation":0,"scale":1,"position":{"pointX":512,"pointY":384},"width":1024,"sublayerTransform":[1,0,0,0,0,1,0,0,0,0,1,0,0,0,0,1],"contentsRect":{"y":0,"x":0,"width":1,"height":1},"opacity":1,"edgeAntialiasingMask":0,"height":768,"hidden":false,"anchorPoint":{"pointX":0.5,"pointY":0.5}},"texture":"92C74656B088334F9F2FD2DB2984453E"}]}]}}]}